torchklip/__init__.py
torchklip/config.py
torchklip/algos/__init__.py
torchklip/algos/klip/__init__.py
torchklip/algos/klip/eigh.py
torchklip/algos/klip/klip_base.py
torchklip/algos/klip/pca.py
torchklip/algos/klip/svd.py
torchklip/dataproc/__init__.py
torchklip/dataproc/data_loader.py
torchklip/dataproc/data_preprocessor.py
torchklip/utils/__init__.py
torchklip/utils/image_plot.py
torchklip/utils/logging_utils.py
torchklip/utils/metrics_renderer.py
torchklip/utils/profiler.py
torchklip/utils/snr.py
torchklip-0.1.0.dist-info/licenses/LICENSE
torchklip-0.1.0.dist-info/METADATA
torchklip-0.1.0.dist-info/WHEEL
torchklip-0.1.0.dist-info/top_level.txt
torchklip-0.1.0.dist-info/RECORD
