Metadata-Version: 2.4
Name: torchklip
Version: 0.1.0
Summary: A Python package for exoplanet data processing, featuring an implementation of the fundamental KLIP algorithm using PyTorch.
Author-email: Chia-Lin Ko <clko@arizona.edu>
License: MIT License
Requires-Python: >=3.11
License-File: LICENSE
Requires-Dist: numpy<2.0,>=1.21
Requires-Dist: astropy>=5.0
Requires-Dist: matplotlib>=3.5
Requires-Dist: scipy>=1.8
Requires-Dist: torch>=1.13
Requires-Dist: torchvision>=0.14
Provides-Extra: dev
Requires-Dist: pytest; extra == "dev"
Requires-Dist: jupyter; extra == "dev"
Requires-Dist: pyklip; extra == "dev"
Requires-Dist: scikit-image; extra == "dev"
Dynamic: license-file
